dpclone/__init__.py
dpclone/__init__.pyi
dpclone/common.py
dpclone/errors.py
dpclone/items.py
dpclone/version.py
dpclone/_base/base.py
dpclone/_base/base.pyi
dpclone/_base/chromium.py
dpclone/_base/chromium.pyi
dpclone/_base/driver.py
dpclone/_base/driver.pyi
dpclone/_configs/chromium_options.py
dpclone/_configs/chromium_options.pyi
dpclone/_configs/configs.ini
dpclone/_configs/options_manage.py
dpclone/_configs/options_manage.pyi
dpclone/_configs/session_options.py
dpclone/_configs/session_options.pyi
dpclone/_elements/chromium_element.py
dpclone/_elements/chromium_element.pyi
dpclone/_elements/none_element.py
dpclone/_elements/none_element.pyi
dpclone/_elements/session_element.py
dpclone/_elements/session_element.pyi
dpclone/_functions/browser.py
dpclone/_functions/browser.pyi
dpclone/_functions/by.py
dpclone/_functions/cli.py
dpclone/_functions/cookies.py
dpclone/_functions/cookies.pyi
dpclone/_functions/elements.py
dpclone/_functions/elements.pyi
dpclone/_functions/keys.py
dpclone/_functions/keys.pyi
dpclone/_functions/locator.py
dpclone/_functions/locator.pyi
dpclone/_functions/settings.py
dpclone/_functions/settings.pyi
dpclone/_functions/suffixes.dat
dpclone/_functions/texts.py
dpclone/_functions/tools.py
dpclone/_functions/tools.pyi
dpclone/_functions/web.py
dpclone/_functions/web.pyi
dpclone/_pages/chromium_base.py
dpclone/_pages/chromium_base.pyi
dpclone/_pages/chromium_frame.py
dpclone/_pages/chromium_frame.pyi
dpclone/_pages/chromium_page.py
dpclone/_pages/chromium_page.pyi
dpclone/_pages/chromium_tab.py
dpclone/_pages/chromium_tab.pyi
dpclone/_pages/mix_tab.py
dpclone/_pages/mix_tab.pyi
dpclone/_pages/session_page.py
dpclone/_pages/session_page.pyi
dpclone/_pages/web_page.py
dpclone/_pages/web_page.pyi
dpclone/_units/actions.py
dpclone/_units/actions.pyi
dpclone/_units/clicker.py
dpclone/_units/clicker.pyi
dpclone/_units/console.py
dpclone/_units/console.pyi
dpclone/_units/cookies_setter.py
dpclone/_units/cookies_setter.pyi
dpclone/_units/downloader.py
dpclone-4.1.0.19.dist-info/licenses/LICENSE
dpclone-4.1.0.19.dist-info/METADATA
dpclone-4.1.0.19.dist-info/WHEEL
dpclone-4.1.0.19.dist-info/entry_points.txt
dpclone-4.1.0.19.dist-info/top_level.txt
dpclone-4.1.0.19.dist-info/RECORD
