Metadata-Version: 2.4
Name: dpclone
Version: 4.1.0.19
Summary: DPClone
Author-email: g1879 <g1879@qq.com>
Maintainer-email: g1879 <g1879@qq.com>
License: MIT
Project-URL: Homepage, https://DrissionPage.cn
Project-URL: Documentation, https://DrissionPage.cn
Project-URL: Repository, https://github.com/g1879/DrissionPage
Project-URL: Issues, https://github.com/g1879/DrissionPage/issues
Keywords: selenium,browser,automation,web,scraping,requests
Classifier: Development Status :: 5 - Production/Stable
Classifier: Intended Audience :: Developers
Classifier: License :: OSI Approved :: MIT License
Classifier: Operating System :: OS Independent
Classifier: Programming Language :: Python :: 3
Classifier: Programming Language :: Python :: 3.8
Classifier: Programming Language :: Python :: 3.9
Classifier: Programming Language :: Python :: 3.10
Classifier: Programming Language :: Python :: 3.11
Classifier: Programming Language :: Python :: 3.12
Classifier: Topic :: Software Development :: Libraries :: Python Modules
Classifier: Topic :: Internet :: WWW/HTTP :: Browsers
Classifier: Topic :: Software Development :: Testing
Requires-Python: >=3.8
License-File: LICENSE
Requires-Dist: requests>=2.28.0
Requires-Dist: lxml>=4.9.0
Requires-Dist: click>=8.0.0
Requires-Dist: DownloadKit>=1.0.0
Requires-Dist: websocket-client>=1.3.0
Requires-Dist: tldextract>=3.4.0
Requires-Dist: DataRecorder>=1.0.0
Provides-Extra: dev
Requires-Dist: pytest>=7.0.0; extra == "dev"
Requires-Dist: pytest-cov>=4.0.0; extra == "dev"
Requires-Dist: black>=22.0.0; extra == "dev"
Requires-Dist: flake8>=5.0.0; extra == "dev"
Provides-Extra: windows
Requires-Dist: pypiwin32>=223; extra == "windows"
Dynamic: license-file
